makeweb/__init__.py
makeweb/defaults.py
makeweb/html.py
makeweb/javascript.py
makeweb/stylesheet.py
makeweb/utilities.py
makeweb-0.2.3.dist-info/LICENSE
makeweb-0.2.3.dist-info/METADATA
makeweb-0.2.3.dist-info/WHEEL
makeweb-0.2.3.dist-info/RECORD
